tbip/__init__.py
tbip/__main__.py
tbip/archive_data.py
tbip/cli.py
tbip/compiler.py
tbip/installer.py
tbip/ui.py
tbip/uiutils/__init__.py
tbip/uiutils/_cli_progress_bar.py
tbip/uiutils/baseitem.py
tbip/uiutils/tree.py
tbip-0.0.0.4.dist-info/METADATA
tbip-0.0.0.4.dist-info/RECORD
tbip-0.0.0.4.dist-info/WHEEL
tbip-0.0.0.4.dist-info/top_level.txt
