Metadata-Version: 2.1
Name: tbip
Version: 0.0.0.4
Summary: Build cross-platform installers
Home-page: https://github.com/Michael78912/tbip
Author: Michael Gill
Author-email: michael.78912.8@gmail.com
License: UNKNOWN
Platform: UNKNOWN
Classifier: Programming Language :: Python :: 3
Classifier: License :: OSI Approved :: MIT License
Classifier: Operating System :: OS Independent
Requires-Dist: colorama
